{
  "invitationCodes": [
    {
      "code": "VIP-DFTDH1NX",
      "type": "normal",
      "generatedDate": "2025-08-26T16:41:30.496Z",
      "expiryDate": "2025-09-02T16:41:30.496Z",
      "used": false,
      "usedBy": null,
      "usedTime": null,
      "usageCount": 0
    },
    {
      "code": "CODE-VTFOQD3B",
      "type": "normal",
      "generatedDate": "2025-08-26T16:23:24.265Z",
      "expiryDate": "2025-09-07T16:23:24.265Z",
      "used": false,
      "usedBy": null,
      "usedTime": null,
      "usageCount": 0
    }
  ],
  "uploadDate": "2025-08-26T16:43:16.019Z",
  "totalCodes": 2,
  "activeCodes": 2
}